errors/__init__.py
errors/base.py
errors/data_classes.py
errors/error.py
errors/mixin.py
errors/settings.py
error_manager-1.4.4.dist-info/LICENSE
error_manager-1.4.4.dist-info/METADATA
error_manager-1.4.4.dist-info/WHEEL
error_manager-1.4.4.dist-info/top_level.txt
error_manager-1.4.4.dist-info/RECORD
