Metadata-Version: 2.1
Name: error-manager
Version: 1.4.4
Summary: Manage error codes, descriptions and data in a unified way throughout a project
Home-page: https://github.com/MaartendeRuyter/errors
Author: Maarten de Ruyter
Author-email: "Maarten de Ruyter" <maarten@geodatagarden.com>
License: GNU
Classifier: License :: OSI Approved :: GNU Lesser General Public License v3 or later (LGPLv3+)
Classifier: Intended Audience :: Developers
Classifier: Programming Language :: Python
Classifier: Programming Language :: Python :: 3
Classifier: Programming Language :: Python :: 3 :: Only
Classifier: Programming Language :: Python :: 3.10
Classifier: Programming Language :: Python :: 3.11
Classifier: Programming Language :: Python :: 3.12
License-File: LICENSE
